stlmc/__init__.py
stlmc/default.cfg
stlmc/3rd_party/dReal3/dReal
stlmc/cli/__init__.py
stlmc/cli/mc.py
stlmc/cli/visualize.py
stlmc/constraints/__init__.py
stlmc/constraints/constraints.py
stlmc/constraints/encoding.py
stlmc/constraints/enhanced_partition.py
stlmc/constraints/enhanced_separation.py
stlmc/constraints/interval.py
stlmc/constraints/operations.py
stlmc/constraints/partition.py
stlmc/constraints/separation.py
stlmc/constraints/translation.py
stlmc/driver/__init__.py
stlmc/driver/abstract_driver.py
stlmc/driver/base_driver.py
stlmc/encoding/__init__.py
stlmc/encoding/enumerate.py
stlmc/encoding/monolithic.py
stlmc/encoding/reach.py
stlmc/encoding/static_learning.py
stlmc/encoding/time.py
stlmc/exception/__init__.py
stlmc/exception/exception.py
stlmc/hybrid_automaton/__init__.py
stlmc/hybrid_automaton/converter.py
stlmc/hybrid_automaton/hybrid_automaton.py
stlmc/hybrid_automaton/utils.py
stlmc/objects/__init__.py
stlmc/objects/algorithm.py
stlmc/objects/algorithm_factory.py
stlmc/objects/configuration.py
stlmc/objects/goal.py
stlmc/objects/model.py
stlmc/objects/object_factory.py
stlmc/objects/proposition.py
stlmc/parser/__init__.py
stlmc/parser/checker.py
stlmc/parser/config_visitor.py
stlmc/parser/error_listener.py
stlmc/parser/model_visitor.py
stlmc/parser/visualize_visitor.py
stlmc/solver/__init__.py
stlmc/solver/abstract_solver.py
stlmc/solver/assignment.py
stlmc/solver/c2e2.py
stlmc/solver/dreal.py
stlmc/solver/flowstar.py
stlmc/solver/hylaa.py
stlmc/solver/new_dreal.py
stlmc/solver/ode_solver.py
stlmc/solver/ode_utils.py
stlmc/solver/solver_factory.py
stlmc/solver/spaceex.py
stlmc/solver/ssmt.py
stlmc/solver/strategy.py
stlmc/solver/yices.py
stlmc/solver/z3.py
stlmc/syntax/.gitignore
stlmc/syntax/config/config.g4
stlmc/syntax/config/config.interp
stlmc/syntax/config/config.tokens
stlmc/syntax/config/configLexer.interp
stlmc/syntax/config/configLexer.py
stlmc-1.0.0.dev3.dist-info/METADATA
stlmc-1.0.0.dev3.dist-info/WHEEL
stlmc-1.0.0.dev3.dist-info/entry_points.txt
stlmc-1.0.0.dev3.dist-info/RECORD
stlmc-1.0.0.dev3.dist-info/licenses/LICENSE
